pandas_dtype_efficiency.py
pandas_dtype_efficiency-0.0.1.dist-info/LICENSE.txt
pandas_dtype_efficiency-0.0.1.dist-info/METADATA
pandas_dtype_efficiency-0.0.1.dist-info/WHEEL
pandas_dtype_efficiency-0.0.1.dist-info/top_level.txt
pandas_dtype_efficiency-0.0.1.dist-info/RECORD
