Metadata-Version: 2.1
Name: pandas-dtype-efficiency
Version: 0.0.1
Summary: Evaluate pandas DataFrames to see whether their memory usage can be reduced without losing information
Home-page: https://github.com/osulki01/pandas_dtype_efficiency
Author: Kieran O'Sullivan
Author-email: osullivank3@hotmail.com
License: MIT
Keywords: data,science,pandas,memory,efficiency
Platform: UNKNOWN
Classifier: Development Status :: 3 - Alpha
Classifier: Intended Audience :: Developers
Classifier: Programming Language :: Python :: 3
Classifier: Programming Language :: Python :: 3.7
Classifier: Topic :: Scientific/Engineering :: Information Analysis
Requires-Python: >=3.7
Requires-Dist: pandas
